RandomNumber/RandomNumbers.py
RandomNumber/__init__.py
randomNumbergen-0.0.14.dist-info/METADATA
randomNumbergen-0.0.14.dist-info/WHEEL
randomNumbergen-0.0.14.dist-info/top_level.txt
randomNumbergen-0.0.14.dist-info/RECORD
