Metadata-Version: 2.1
Name: randomNumbergen
Version: 0.0.14
Summary: Generate random numbers
Author: teilorr
Author-email: rejija5117@abincol.com
License: UNKNOWN
Keywords: random,randomNumber
Platform: UNKNOWN
Classifier: Intended Audience :: Developers
Classifier: Programming Language :: Python :: 3
Classifier: Operating System :: Unix
Classifier: Operating System :: MacOS :: MacOS X
Classifier: Operating System :: Microsoft :: Windows
